mouser/__init__.py
mouser/api.py
mouser/base.py
mouser/cli.py
mouser-0.1.6.dist-info/LICENSE
mouser-0.1.6.dist-info/METADATA
mouser-0.1.6.dist-info/WHEEL
mouser-0.1.6.dist-info/entry_points.txt
mouser-0.1.6.dist-info/RECORD
