Metadata-Version: 2.1
Name: mouser
Version: 0.1.6
Summary: Mouser Python API
Home-page: https://github.com/sparkmicro/mouser-api
License: MIT
Keywords: mouser,api,python
Author: eeintech
Author-email: eeintech@eeinte.ch
Maintainer: eeintech
Maintainer-email: eeintech@eeinte.ch
Requires-Python: >=3.8,<4.0
Classifier: License :: OSI Approved :: MIT License
Classifier: Programming Language :: Python :: 3
Classifier: Programming Language :: Python :: 3.8
Classifier: Programming Language :: Python :: 3.9
Classifier: Programming Language :: Python :: 3.10
Classifier: Programming Language :: Python :: 3.11
Requires-Dist: click (>=8.1,<9.0)
Requires-Dist: requests (>=2.31,<3.0)
Project-URL: Repository, https://github.com/sparkmicro/mouser-api
